[
{
"id": "hold-2i8h4o",
"title": "Hold tight 2i8h4o",
"filename": "2i8h4o.mp3",
"type": "full_reise",
"inhale": 2,
"exhale": 4,
"holdIn": 8,
"holdOut": 0,
"hasBreathLogic": true,
"startPhase": "inhale",
"breathPattern": ["inhale", "holdIn", "exhale"],
"durationSec": 612,
"mood": "intense",
"energy": "medium",
"playlistRole": ["start"],
"notes": "Kort innpust, lang hold"
},
{
"id": "sleep-4i7h8o",
"title": "4i7h8o Sleep",
"filename": "4i7h8o-sleep.mp3",
"type": "full_reise",
"inhale": 4,
"exhale": 8,
"holdIn": 7,
"holdOut": 0,
"hasBreathLogic": true,
"startPhase": "inhale",
"breathPattern": ["inhale", "holdIn", "exhale"],
"durationSec": 618,
"mood": "sleep",
"energy": "low",
"playlistRole": ["end"]
},

{
"id": "vagus-energy-5i5o",
"title": "Vagus Energy",
"filename": "Vagus-Energy-5i5o.mp3",
"type": "full_reise",
"inhale": 5,
"exhale": 5,
"holdIn": 0,
"holdOut": 0,
"hasBreathLogic": true,
"startPhase": "inhale",
"breathPattern": ["inhale", "exhale"],
"durationSec": 615,
"mood": "clear",
"energy": "medium_high",
"playlistRole": ["start"]
},
{
"id": "vagus-focus-5i5o",
"title": "Vagus Focus",
"filename": "Vagus-Focus-5i5o.mp3",
"type": "full_reise",
"inhale": 5,
"exhale": 5,
"holdIn": 0,
"holdOut": 0,
"hasBreathLogic": true,
"startPhase": "inhale",
"breathPattern": ["inhale", "exhale"],
"durationSec": 605,
"mood": "focus",
"energy": "medium",
"playlistRole": ["middle"]
},
{
"id": "vagus-sleep-5i5o",
"title": "Vagus Sleep",
"filename": "Vagus-Sleep-5i5o.mp3",
"type": "full_reise",
"inhale": 5,
"exhale": 5,
"holdIn": 0,
"holdOut": 0,
"hasBreathLogic": true,
"startPhase": "inhale",
"breathPattern": ["inhale", "exhale"],
"durationSec": 610,
"mood": "sleep",
"energy": "low",
"playlistRole": ["end"]
},

{
"id": "triadisk-5o5h5i",
"title": "Triadisk hold to release",
"filename": "Triadisk-5o5h5i.mp3",
"type": "full_reise",
"inhale": 5,
"exhale": 5,
"holdIn": 5,
"holdOut": 0,
"hasBreathLogic": true,
"startPhase": "exhale",
"breathPattern": ["exhale", "holdIn", "inhale"],
"durationSec": 610,
"mood": "deep",
"energy": "medium",
"playlistRole": ["middle"],
"notes": "Starter med utpust"
},

{
"id": "coherence1-6i6o",
"title": "Coherence 1",
"filename": "Coherence1-6i6o.mp3",
"type": "byggekloss",
"inhale": 6,
"exhale": 6,
"holdIn": 0,
"holdOut": 0,
"hasBreathLogic": true,
"startPhase": "inhale",
"breathPattern": ["inhale", "exhale"],
"durationSec": 144,
"mood": "stable",
"energy": "low",
"playlistRole": ["start", "middle"]
},
{
"id": "coherence2-6i6o",
"title": "Coherence 2",
"filename": "Coherence2-6i6o.mp3",
"type": "byggekloss",
"inhale": 6,
"exhale": 6,
"holdIn": 0,
"holdOut": 0,
"hasBreathLogic": true,
"startPhase": "inhale",
"breathPattern": ["inhale", "exhale"],
"durationSec": 144,
"mood": "balanced",
"energy": "low_medium",
"playlistRole": ["middle"]
},

{
"id": "peace-4i8o",
"title": "Peace 4:8",
"filename": "Peace-4i8o.mp3",
"type": "byggekloss",
"inhale": 4,
"exhale": 8,
"holdIn": 0,
"holdOut": 0,
"hasBreathLogic": true,
"startPhase": "inhale",
"breathPattern": ["inhale", "exhale"],
"durationSec": 48,
"mood": "light_calm",
"energy": "low",
"playlistRole": ["start", "middle"]
},
{
"id": "peace-5i10o",
"title": "Peace 5:10",
"filename": "Peace-5i10o.mp3",
"type": "byggekloss",
"inhale": 5,
"exhale": 10,
"holdIn": 0,
"holdOut": 0,
"hasBreathLogic": true,
"startPhase": "inhale",
"breathPattern": ["inhale", "exhale"],
"durationSec": 60,
"mood": "soft",
"energy": "low",
"playlistRole": ["middle", "end"]
},
{
"id": "peace-6i12o",
"title": "Peace 6:12",
"filename": "Peace-6i12o.mp3",
"type": "byggekloss",
"inhale": 6,
"exhale": 12,
"holdIn": 0,
"holdOut": 0,
"hasBreathLogic": true,
"startPhase": "inhale",
"breathPattern": ["inhale", "exhale"],
"durationSec": 72,
"mood": "deep_calm",
"energy": "low",
"playlistRole": ["middle", "end"]
},

{
"id": "ambient-weightless",
"title": "Weightless",
"filename": "Ambient-music-Weightless.mp3",
"type": "pause",
"hasBreathLogic": false
},
{
"id": "bell-4-per-minute",
"title": "Bell 4/min",
"filename": "Bell-4-pr-minute.mp3",
"type": "pause",
"hasBreathLogic": false
},
{
"id": "birds-spring",
"title": "Birds Spring",
"filename": "Ambience-Birds-Spring.mp3",
"type": "pause",
"hasBreathLogic": false
}
]
